{
  "state": "NAGALAND",
  "row_count": 5,
  "districts": [
    "DIMAPUR",
    "KIPHIRE",
    "KOHIMA",
    "MOKOKCHUNG",
    "WOKHA"
  ],
  "rows": [
    {
      "date": "2026-04-13",
      "period_start": "2026-03-01",
      "period_end": "2026-04-13",
      "level": "district",
      "subdivision": "NMMT",
      "state": "NAGALAND",
      "district": "DIMAPUR",
      "day_actual_mm": 0.0,
      "day_normal_mm": 2.2,
      "day_departure_pct": -100.0,
      "day_category": "NR",
      "period_actual_mm": 87.0,
      "period_normal_mm": 55.7,
      "period_departure_pct": 56.0,
      "period_category": "E",
      "scraped_at": "2026-04-13T11:45:17"
    },
    {
      "date": "2026-04-13",
      "period_start": "2026-03-01",
      "period_end": "2026-04-13",
      "level": "district",
      "subdivision": "NMMT",
      "state": "NAGALAND",
      "district": "KIPHIRE",
      "day_actual_mm": 0.0,
      "day_normal_mm": 2.0,
      "day_departure_pct": -100.0,
      "day_category": "NR",
      "period_actual_mm": 126.6,
      "period_normal_mm": 43.8,
      "period_departure_pct": 189.0,
      "period_category": "LE",
      "scraped_at": "2026-04-13T11:45:17"
    },
    {
      "date": "2026-04-13",
      "period_start": "2026-03-01",
      "period_end": "2026-04-13",
      "level": "district",
      "subdivision": "NMMT",
      "state": "NAGALAND",
      "district": "KOHIMA",
      "day_actual_mm": 0.0,
      "day_normal_mm": 2.1,
      "day_departure_pct": -100.0,
      "day_category": "NR",
      "period_actual_mm": 204.3,
      "period_normal_mm": 102.8,
      "period_departure_pct": 99.0,
      "period_category": "LE",
      "scraped_at": "2026-04-13T11:45:17"
    },
    {
      "date": "2026-04-13",
      "period_start": "2026-03-01",
      "period_end": "2026-04-13",
      "level": "district",
      "subdivision": "NMMT",
      "state": "NAGALAND",
      "district": "MOKOKCHUNG",
      "day_actual_mm": 12.9,
      "day_normal_mm": 4.0,
      "day_departure_pct": 223.0,
      "day_category": "LE",
      "period_actual_mm": 184.0,
      "period_normal_mm": 131.1,
      "period_departure_pct": 40.0,
      "period_category": "E",
      "scraped_at": "2026-04-13T11:45:17"
    },
    {
      "date": "2026-04-13",
      "period_start": "2026-03-01",
      "period_end": "2026-04-13",
      "level": "district",
      "subdivision": "NMMT",
      "state": "NAGALAND",
      "district": "WOKHA",
      "day_actual_mm": 0.0,
      "day_normal_mm": 3.1,
      "day_departure_pct": -100.0,
      "day_category": "NR",
      "period_actual_mm": 113.2,
      "period_normal_mm": 100.8,
      "period_departure_pct": 12.0,
      "period_category": "N",
      "scraped_at": "2026-04-13T11:45:17"
    }
  ]
}