{
  "state": "ASSAM",
  "district": "KOKRAJHAR",
  "row_count": 2,
  "rows": [
    {
      "date": "2026-04-17",
      "period_start": "2026-03-01",
      "period_end": "2026-04-17",
      "level": "district",
      "subdivision": "ASSAM & MEGHALAYA",
      "state": "ASSAM",
      "district": "KOKRAJHAR",
      "day_actual_mm": 0.0,
      "day_normal_mm": 7.1,
      "day_departure_pct": -100.0,
      "day_category": "NR",
      "period_actual_mm": 362.3,
      "period_normal_mm": 128.5,
      "period_departure_pct": 182.0,
      "period_category": "LE",
      "scraped_at": "2026-04-20T07:43:09"
    },
    {
      "date": "2026-04-18",
      "period_start": "2026-03-01",
      "period_end": "2026-04-18",
      "level": "district",
      "subdivision": "ASSAM & MEGHALAYA",
      "state": "ASSAM",
      "district": "KOKRAJHAR",
      "day_actual_mm": 0.0,
      "day_normal_mm": 5.8,
      "day_departure_pct": -100.0,
      "day_category": "NR",
      "period_actual_mm": 362.3,
      "period_normal_mm": 134.3,
      "period_departure_pct": 170.0,
      "period_category": "LE",
      "scraped_at": "2026-04-20T07:43:11"
    }
  ]
}